bluetooth/__init__.py
bluetooth/_msbt.cp39-win_amd64.pyd
bluetooth/ble.py
bluetooth/bluez.py
bluetooth/btcommon.py
bluetooth/macos.py
bluetooth/msbt.py
PyBluezovenlab-0.30.dist-info/COPYING
PyBluezovenlab-0.30.dist-info/METADATA
PyBluezovenlab-0.30.dist-info/WHEEL
PyBluezovenlab-0.30.dist-info/eager_resources.txt
PyBluezovenlab-0.30.dist-info/top_level.txt
PyBluezovenlab-0.30.dist-info/zip-safe
PyBluezovenlab-0.30.dist-info/RECORD
